pypowermate/__init__.py
pypowermate/powermate.py
pypowermate-2.0.2.dist-info/LICENSE.txt
pypowermate-2.0.2.dist-info/METADATA
pypowermate-2.0.2.dist-info/WHEEL
pypowermate-2.0.2.dist-info/top_level.txt
pypowermate-2.0.2.dist-info/RECORD
